{"ts_code":"600285.SH","name":"羚锐制药","count":120,"kline":[{"trade_date":"20260123","open":20.92,"high":21.1,"low":20.9,"close":21.02,"pre_close":20.92,"vol":67752.26,"amount":142508.443},{"trade_date":"20260126","open":21.11,"high":21.6,"low":20.78,"close":21.53,"pre_close":21.02,"vol":151289.01,"amount":321708.778},{"trade_date":"20260127","open":21.6,"high":21.64,"low":21.18,"close":21.42,"pre_close":21.53,"vol":70350.22,"amount":150539.603},{"trade_date":"20260128","open":21.32,"high":21.45,"low":21.17,"close":21.34,"pre_close":21.42,"vol":53945.3,"amount":114951.593},{"trade_date":"20260129","open":21.35,"high":21.83,"low":21.34,"close":21.77,"pre_close":21.34,"vol":103934.05,"amount":225370.111},{"trade_date":"20260130","open":21.88,"high":22.25,"low":21.74,"close":21.96,"pre_close":21.77,"vol":130998.14,"amount":288869.087},{"trade_date":"20260202","open":21.97,"high":22.2,"low":21.48,"close":21.54,"pre_close":21.96,"vol":83824.39,"amount":182914.539},{"trade_date":"20260203","open":21.6,"high":21.9,"low":21.56,"close":21.88,"pre_close":21.54,"vol":81193.22,"amount":176738.106},{"trade_date":"20260204","open":21.88,"high":22.54,"low":21.73,"close":22.4,"pre_close":21.88,"vol":130848.87,"amount":291675.782},{"trade_date":"20260205","open":22.5,"high":22.58,"low":22.25,"close":22.42,"pre_close":22.4,"vol":85724.05,"amount":192493.806},{"trade_date":"20260206","open":22.76,"high":22.88,"low":22.23,"close":22.24,"pre_close":22.42,"vol":97615.64,"amount":219734.349},{"trade_date":"20260209","open":22.19,"high":22.33,"low":22.0,"close":22.15,"pre_close":22.24,"vol":79630.73,"amount":176244.473},{"trade_date":"20260210","open":22.17,"high":22.17,"low":21.97,"close":22.07,"pre_close":22.15,"vol":43126.95,"amount":95170.921},{"trade_date":"20260211","open":22.11,"high":22.14,"low":21.92,"close":21.95,"pre_close":22.07,"vol":35239.56,"amount":77554.208},{"trade_date":"20260212","open":22.0,"high":22.0,"low":21.67,"close":21.79,"pre_close":21.95,"vol":51863.56,"amount":112915.908},{"trade_date":"20260213","open":21.78,"high":21.85,"low":21.45,"close":21.47,"pre_close":21.79,"vol":40313.12,"amount":87241.5},{"trade_date":"20260224","open":21.65,"high":21.79,"low":21.42,"close":21.6,"pre_close":21.47,"vol":58094.29,"amount":125667.578},{"trade_date":"20260225","open":21.63,"high":21.89,"low":21.49,"close":21.53,"pre_close":21.6,"vol":65687.0,"amount":142381.128},{"trade_date":"20260226","open":21.6,"high":21.74,"low":21.4,"close":21.53,"pre_close":21.53,"vol":61900.03,"amount":133470.123},{"trade_date":"20260227","open":21.5,"high":21.61,"low":21.43,"close":21.59,"pre_close":21.53,"vol":39116.57,"amount":84277.82},{"trade_date":"20260302","open":21.57,"high":21.68,"low":21.37,"close":21.66,"pre_close":21.59,"vol":59659.71,"amount":128667.97},{"trade_date":"20260303","open":21.63,"high":22.07,"low":21.58,"close":21.77,"pre_close":21.66,"vol":93304.52,"amount":203530.542},{"trade_date":"20260304","open":21.61,"high":21.74,"low":21.02,"close":21.21,"pre_close":21.77,"vol":92175.55,"amount":196362.517},{"trade_date":"20260305","open":21.35,"high":21.46,"low":21.19,"close":21.32,"pre_close":21.21,"vol":52520.0,"amount":111902.229},{"trade_date":"20260306","open":21.3,"high":21.58,"low":21.2,"close":21.51,"pre_close":21.32,"vol":54383.0,"amount":116730.954},{"trade_date":"20260309","open":21.44,"high":21.48,"low":21.17,"close":21.19,"pre_close":21.51,"vol":61877.98,"amount":131903.182},{"trade_date":"20260310","open":21.3,"high":21.56,"low":21.23,"close":21.45,"pre_close":21.19,"vol":39312.82,"amount":84086.013},{"trade_date":"20260311","open":21.51,"high":21.52,"low":21.23,"close":21.38,"pre_close":21.45,"vol":49551.65,"amount":105679.111},{"trade_date":"20260312","open":21.34,"high":21.87,"low":21.34,"close":21.79,"pre_close":21.38,"vol":85994.02,"amount":186263.449},{"trade_date":"20260313","open":21.75,"high":22.5,"low":21.75,"close":22.05,"pre_close":21.79,"vol":126040.68,"amount":279823.851},{"trade_date":"20260316","open":22.05,"high":22.18,"low":21.73,"close":21.75,"pre_close":22.05,"vol":64339.25,"amount":141067.689},{"trade_date":"20260317","open":21.78,"high":22.66,"low":21.78,"close":22.35,"pre_close":21.75,"vol":117466.73,"amount":262260.989},{"trade_date":"20260318","open":22.35,"high":22.45,"low":22.0,"close":22.18,"pre_close":22.35,"vol":67945.37,"amount":150540.807},{"trade_date":"20260319","open":22.02,"high":22.24,"low":21.89,"close":22.04,"pre_close":22.18,"vol":59127.82,"amount":130362.47},{"trade_date":"20260320","open":22.04,"high":22.9,"low":22.0,"close":22.49,"pre_close":22.04,"vol":141092.24,"amount":319129.016},{"trade_date":"20260323","open":22.24,"high":22.4,"low":21.58,"close":21.75,"pre_close":22.49,"vol":116411.85,"amount":255775.175},{"trade_date":"20260324","open":22.1,"high":22.11,"low":21.15,"close":21.79,"pre_close":21.75,"vol":124280.69,"amount":268108.496},{"trade_date":"20260325","open":21.8,"high":22.1,"low":21.63,"close":22.04,"pre_close":21.79,"vol":63858.86,"amount":139947.893},{"trade_date":"20260326","open":21.91,"high":22.26,"low":21.85,"close":22.04,"pre_close":22.04,"vol":59216.79,"amount":130623.313},{"trade_date":"20260327","open":21.92,"high":22.55,"low":21.85,"close":22.28,"pre_close":22.04,"vol":66415.54,"amount":148317.79},{"trade_date":"20260330","open":22.24,"high":22.73,"low":22.19,"close":22.6,"pre_close":22.28,"vol":83639.47,"amount":188513.177},{"trade_date":"20260331","open":22.6,"high":22.79,"low":22.33,"close":22.35,"pre_close":22.6,"vol":47443.44,"amount":106697.026},{"trade_date":"20260401","open":22.6,"high":22.78,"low":22.41,"close":22.49,"pre_close":22.35,"vol":65652.98,"amount":148206.14},{"trade_date":"20260402","open":22.54,"high":22.59,"low":22.33,"close":22.5,"pre_close":22.49,"vol":55784.23,"amount":125224.471},{"trade_date":"20260403","open":22.44,"high":22.49,"low":21.93,"close":21.99,"pre_close":22.5,"vol":48992.34,"amount":108519.629},{"trade_date":"20260407","open":22.12,"high":22.13,"low":21.62,"close":21.96,"pre_close":21.99,"vol":56163.09,"amount":122734.697},{"trade_date":"20260408","open":22.12,"high":22.21,"low":21.94,"close":22.18,"pre_close":21.96,"vol":82066.69,"amount":181065.587},{"trade_date":"20260409","open":22.04,"high":22.19,"low":21.78,"close":21.9,"pre_close":22.18,"vol":60653.0,"amount":132965.074},{"trade_date":"20260410","open":21.91,"high":21.99,"low":21.67,"close":21.68,"pre_close":21.9,"vol":58895.65,"amount":128365.799},{"trade_date":"20260413","open":21.65,"high":21.79,"low":21.4,"close":21.55,"pre_close":21.68,"vol":49877.0,"amount":107563.59},{"trade_date":"20260414","open":21.61,"high":21.61,"low":21.2,"close":21.46,"pre_close":21.55,"vol":90487.75,"amount":193051.703},{"trade_date":"20260415","open":21.48,"high":21.69,"low":21.39,"close":21.6,"pre_close":21.46,"vol":66358.02,"amount":143057.565},{"trade_date":"20260416","open":21.65,"high":21.68,"low":21.1,"close":21.24,"pre_close":21.6,"vol":116049.32,"amount":246990.185},{"trade_date":"20260417","open":21.3,"high":21.3,"low":21.02,"close":21.08,"pre_close":21.24,"vol":69493.01,"amount":146499.906},{"trade_date":"20260420","open":21.06,"high":21.32,"low":21.0,"close":21.16,"pre_close":21.08,"vol":65619.34,"amount":138824.794},{"trade_date":"20260421","open":21.19,"high":21.59,"low":21.11,"close":21.54,"pre_close":21.16,"vol":78804.25,"amount":168553.987},{"trade_date":"20260422","open":21.54,"high":21.69,"low":21.44,"close":21.52,"pre_close":21.54,"vol":50111.37,"amount":108065.942},{"trade_date":"20260423","open":21.5,"high":21.59,"low":21.38,"close":21.44,"pre_close":21.52,"vol":53270.54,"amount":114358.086},{"trade_date":"20260424","open":21.48,"high":21.7,"low":21.27,"close":21.59,"pre_close":21.44,"vol":56684.06,"amount":121953.369},{"trade_date":"20260427","open":21.59,"high":21.73,"low":21.24,"close":21.45,"pre_close":21.59,"vol":74189.37,"amount":159211.941},{"trade_date":"20260428","open":22.34,"high":22.85,"low":22.34,"close":22.57,"pre_close":21.45,"vol":262027.94,"amount":591173.438},{"trade_date":"20260429","open":22.43,"high":22.57,"low":22.35,"close":22.56,"pre_close":22.57,"vol":119417.19,"amount":268545.901},{"trade_date":"20260430","open":22.42,"high":22.93,"low":22.36,"close":22.36,"pre_close":22.56,"vol":85312.39,"amount":192268.508},{"trade_date":"20260506","open":22.36,"high":22.36,"low":21.97,"close":22.19,"pre_close":22.36,"vol":107150.44,"amount":237545.114},{"trade_date":"20260507","open":22.21,"high":22.43,"low":22.0,"close":22.19,"pre_close":22.19,"vol":72979.5,"amount":162068.348},{"trade_date":"20260508","open":22.15,"high":22.29,"low":21.96,"close":22.01,"pre_close":22.19,"vol":55009.94,"amount":121338.173},{"trade_date":"20260511","open":22.03,"high":22.08,"low":21.76,"close":21.83,"pre_close":22.01,"vol":81945.8,"amount":179201.504},{"trade_date":"20260512","open":21.85,"high":21.9,"low":21.5,"close":21.78,"pre_close":21.83,"vol":106549.37,"amount":230992.368},{"trade_date":"20260513","open":21.75,"high":21.97,"low":21.66,"close":21.81,"pre_close":21.78,"vol":58761.32,"amount":127942.167},{"trade_date":"20260514","open":21.79,"high":22.05,"low":21.66,"close":21.98,"pre_close":21.81,"vol":69660.23,"amount":152424.467},{"trade_date":"20260515","open":21.88,"high":22.31,"low":21.71,"close":22.06,"pre_close":21.98,"vol":100821.5,"amount":222492.996},{"trade_date":"20260518","open":22.1,"high":22.12,"low":21.54,"close":21.77,"pre_close":22.06,"vol":107382.76,"amount":233413.966},{"trade_date":"20260519","open":21.75,"high":22.22,"low":21.68,"close":22.05,"pre_close":21.77,"vol":67241.78,"amount":148257.113},{"trade_date":"20260520","open":22.08,"high":22.17,"low":21.73,"close":21.79,"pre_close":22.05,"vol":43194.9,"amount":94277.224},{"trade_date":"20260521","open":21.82,"high":21.98,"low":21.53,"close":21.55,"pre_close":21.79,"vol":51149.54,"amount":111170.91},{"trade_date":"20260522","open":21.65,"high":21.67,"low":21.31,"close":21.37,"pre_close":21.55,"vol":57540.83,"amount":123294.361},{"trade_date":"20260525","open":21.37,"high":21.52,"low":21.19,"close":21.23,"pre_close":21.37,"vol":50875.86,"amount":108467.92},{"trade_date":"20260526","open":21.2,"high":21.72,"low":21.19,"close":21.57,"pre_close":21.23,"vol":49389.0,"amount":106375.361},{"trade_date":"20260527","open":21.54,"high":21.65,"low":21.32,"close":21.61,"pre_close":21.57,"vol":41288.88,"amount":88734.093},{"trade_date":"20260528","open":21.51,"high":21.62,"low":21.21,"close":21.25,"pre_close":21.61,"vol":60476.67,"amount":129094.627},{"trade_date":"20260529","open":21.25,"high":21.6,"low":21.1,"close":21.38,"pre_close":21.25,"vol":77409.31,"amount":165520.661},{"trade_date":"20260601","open":21.38,"high":21.95,"low":21.36,"close":21.9,"pre_close":21.38,"vol":98942.5,"amount":214660.286},{"trade_date":"20260602","open":21.89,"high":22.21,"low":21.85,"close":22.05,"pre_close":21.9,"vol":76766.64,"amount":169407.011},{"trade_date":"20260603","open":22.01,"high":22.05,"low":21.4,"close":21.6,"pre_close":22.05,"vol":54062.0,"amount":116968.69},{"trade_date":"20260604","open":21.59,"high":21.74,"low":21.36,"close":21.38,"pre_close":21.6,"vol":39938.17,"amount":85830.659},{"trade_date":"20260605","open":21.5,"high":21.93,"low":21.43,"close":21.76,"pre_close":21.38,"vol":52813.24,"amount":114801.975},{"trade_date":"20260608","open":21.76,"high":21.85,"low":21.37,"close":21.59,"pre_close":21.76,"vol":58928.0,"amount":127057.6},{"trade_date":"20260609","open":21.59,"high":21.71,"low":21.42,"close":21.55,"pre_close":21.59,"vol":52104.95,"amount":112206.411},{"trade_date":"20260610","open":21.54,"high":22.05,"low":21.38,"close":22.0,"pre_close":21.55,"vol":89057.78,"amount":194454.778},{"trade_date":"20260611","open":20.9,"high":21.0,"low":20.62,"close":20.65,"pre_close":20.9,"vol":89034.71,"amount":185302.636},{"trade_date":"20260612","open":20.7,"high":20.88,"low":20.45,"close":20.83,"pre_close":20.65,"vol":78087.5,"amount":161534.444},{"trade_date":"20260615","open":20.76,"high":21.0,"low":20.67,"close":20.98,"pre_close":20.83,"vol":72808.54,"amount":152021.527},{"trade_date":"20260616","open":20.88,"high":20.97,"low":20.5,"close":20.67,"pre_close":20.98,"vol":63841.45,"amount":131727.062},{"trade_date":"20260617","open":20.67,"high":20.67,"low":20.35,"close":20.45,"pre_close":20.67,"vol":39456.66,"amount":80641.242},{"trade_date":"20260618","open":20.39,"high":20.41,"low":20.09,"close":20.12,"pre_close":20.45,"vol":54633.61,"amount":110407.653},{"trade_date":"20260622","open":20.13,"high":20.15,"low":19.16,"close":19.93,"pre_close":20.12,"vol":110348.58,"amount":216565.671},{"trade_date":"20260623","open":19.75,"high":20.17,"low":19.72,"close":20.02,"pre_close":19.93,"vol":56718.31,"amount":113424.316},{"trade_date":"20260624","open":20.17,"high":20.39,"low":19.77,"close":19.79,"pre_close":20.02,"vol":54995.89,"amount":110249.681},{"trade_date":"20260625","open":19.68,"high":19.77,"low":19.19,"close":19.37,"pre_close":19.79,"vol":87590.15,"amount":169835.396},{"trade_date":"20260626","open":19.33,"high":19.48,"low":19.03,"close":19.37,"pre_close":19.37,"vol":64361.5,"amount":123777.786},{"trade_date":"20260629","open":19.37,"high":20.12,"low":19.0,"close":19.91,"pre_close":19.37,"vol":98730.69,"amount":194901.183},{"trade_date":"20260630","open":19.91,"high":19.98,"low":19.23,"close":19.38,"pre_close":19.91,"vol":69237.66,"amount":135081.834},{"trade_date":"20260701","open":19.38,"high":20.05,"low":19.12,"close":19.97,"pre_close":19.38,"vol":75738.99,"amount":148904.183},{"trade_date":"20260702","open":19.97,"high":20.65,"low":19.85,"close":20.62,"pre_close":19.97,"vol":90007.19,"amount":182768.39},{"trade_date":"20260703","open":20.55,"high":20.88,"low":20.48,"close":20.73,"pre_close":20.62,"vol":62368.63,"amount":128979.269},{"trade_date":"20260706","open":20.73,"high":21.35,"low":20.42,"close":21.31,"pre_close":20.73,"vol":105071.5,"amount":221425.908},{"trade_date":"20260707","open":21.2,"high":21.59,"low":20.83,"close":21.45,"pre_close":21.31,"vol":102998.75,"amount":219457.972},{"trade_date":"20260708","open":21.45,"high":22.08,"low":21.15,"close":21.9,"pre_close":21.45,"vol":105476.09,"amount":229765.312},{"trade_date":"20260709","open":21.69,"high":22.18,"low":21.68,"close":21.79,"pre_close":21.9,"vol":88599.32,"amount":194203.906},{"trade_date":"20260710","open":21.85,"high":22.02,"low":21.39,"close":21.72,"pre_close":21.79,"vol":89686.14,"amount":194676.801},{"trade_date":"20260713","open":21.99,"high":22.99,"low":21.86,"close":22.66,"pre_close":21.72,"vol":204131.11,"amount":460422.642},{"trade_date":"20260714","open":22.44,"high":22.96,"low":22.31,"close":22.7,"pre_close":22.66,"vol":162142.75,"amount":369013.952},{"trade_date":"20260715","open":22.66,"high":23.0,"low":22.32,"close":22.92,"pre_close":22.7,"vol":162704.96,"amount":369562.441},{"trade_date":"20260716","open":22.65,"high":23.18,"low":22.61,"close":23.05,"pre_close":22.92,"vol":138381.5,"amount":316899.064},{"trade_date":"20260717","open":23.0,"high":23.34,"low":22.38,"close":22.4,"pre_close":23.05,"vol":164580.58,"amount":375588.595},{"trade_date":"20260720","open":22.25,"high":22.99,"low":22.24,"close":22.8,"pre_close":22.4,"vol":141754.09,"amount":321602.687},{"trade_date":"20260721","open":22.69,"high":22.98,"low":22.36,"close":22.41,"pre_close":22.8,"vol":132823.04,"amount":300782.898},{"trade_date":"20260722","open":22.34,"high":22.5,"low":21.85,"close":22.42,"pre_close":22.41,"vol":134027.0,"amount":297294.188},{"trade_date":"20260723","open":22.42,"high":22.74,"low":22.3,"close":22.61,"pre_close":22.42,"vol":75029.73,"amount":169139.43},{"trade_date":"20260724","open":22.55,"high":22.64,"low":21.89,"close":21.91,"pre_close":22.61,"vol":69942.71,"amount":155371.116}],"signal_dates":["20260724"],"generated_at":"2026-07-24T09:32:51+00:00"}