{"ts_code":"600397.SH","name":"江钨装备","count":120,"kline":[{"trade_date":"20260112","open":9.24,"high":9.92,"low":9.0,"close":9.41,"pre_close":9.06,"vol":866262.38,"amount":821039.161},{"trade_date":"20260113","open":9.54,"high":9.73,"low":9.17,"close":9.2,"pre_close":9.41,"vol":570968.82,"amount":536616.552},{"trade_date":"20260114","open":9.17,"high":9.42,"low":9.09,"close":9.24,"pre_close":9.2,"vol":441510.17,"amount":409163.433},{"trade_date":"20260115","open":9.23,"high":9.63,"low":9.21,"close":9.4,"pre_close":9.24,"vol":386855.83,"amount":364318.342},{"trade_date":"20260116","open":9.46,"high":9.98,"low":9.39,"close":9.42,"pre_close":9.4,"vol":489756.0,"amount":473932.232},{"trade_date":"20260119","open":9.4,"high":10.21,"low":9.2,"close":10.08,"pre_close":9.42,"vol":541824.71,"amount":529379.19},{"trade_date":"20260120","open":10.18,"high":10.66,"low":9.22,"close":9.49,"pre_close":10.08,"vol":781202.08,"amount":754384.685},{"trade_date":"20260121","open":9.59,"high":10.05,"low":9.34,"close":9.88,"pre_close":9.49,"vol":470945.0,"amount":461027.72},{"trade_date":"20260122","open":9.94,"high":10.17,"low":9.7,"close":10.14,"pre_close":9.88,"vol":476255.62,"amount":476351.913},{"trade_date":"20260123","open":10.07,"high":10.88,"low":10.01,"close":10.65,"pre_close":10.14,"vol":550251.01,"amount":580593.955},{"trade_date":"20260126","open":10.75,"high":11.24,"low":10.74,"close":10.94,"pre_close":10.65,"vol":575110.02,"amount":631236.067},{"trade_date":"20260127","open":10.88,"high":11.46,"low":10.68,"close":11.05,"pre_close":10.94,"vol":646624.84,"amount":716429.507},{"trade_date":"20260128","open":10.9,"high":11.05,"low":10.56,"close":10.89,"pre_close":11.05,"vol":490709.08,"amount":529033.182},{"trade_date":"20260129","open":10.88,"high":10.89,"low":10.1,"close":10.12,"pre_close":10.89,"vol":631576.78,"amount":656118.696},{"trade_date":"20260130","open":9.97,"high":10.15,"low":9.59,"close":10.02,"pre_close":10.12,"vol":502137.02,"amount":495136.326},{"trade_date":"20260202","open":9.8,"high":10.77,"low":9.7,"close":10.24,"pre_close":10.02,"vol":682474.76,"amount":713008.738},{"trade_date":"20260203","open":10.52,"high":10.96,"low":10.24,"close":10.95,"pre_close":10.24,"vol":456224.26,"amount":486193.424},{"trade_date":"20260204","open":11.22,"high":11.41,"low":11.01,"close":11.39,"pre_close":10.95,"vol":510461.05,"amount":574046.367},{"trade_date":"20260205","open":11.51,"high":11.86,"low":10.78,"close":10.87,"pre_close":11.39,"vol":592285.81,"amount":659098.354},{"trade_date":"20260206","open":10.78,"high":11.19,"low":10.73,"close":10.99,"pre_close":10.87,"vol":343420.02,"amount":377259.487},{"trade_date":"20260209","open":11.27,"high":11.72,"low":10.82,"close":11.55,"pre_close":10.99,"vol":438706.14,"amount":496757.691},{"trade_date":"20260210","open":11.55,"high":12.04,"low":11.47,"close":11.83,"pre_close":11.55,"vol":382718.02,"amount":451097.437},{"trade_date":"20260211","open":11.94,"high":13.01,"low":11.78,"close":13.01,"pre_close":11.83,"vol":648897.43,"amount":828793.409},{"trade_date":"20260212","open":14.24,"high":14.31,"low":14.23,"close":14.31,"pre_close":13.01,"vol":493897.24,"amount":705646.174},{"trade_date":"20260213","open":14.6,"high":15.74,"low":14.6,"close":15.49,"pre_close":14.31,"vol":1744624.07,"amount":2717326.627},{"trade_date":"20260224","open":16.18,"high":17.04,"low":16.08,"close":17.04,"pre_close":15.49,"vol":581965.99,"amount":980869.047},{"trade_date":"20260225","open":17.64,"high":18.74,"low":16.83,"close":18.74,"pre_close":17.04,"vol":1720841.16,"amount":3035919.017},{"trade_date":"20260226","open":19.12,"high":20.44,"low":19.03,"close":19.57,"pre_close":18.74,"vol":1522606.31,"amount":2985106.44},{"trade_date":"20260227","open":19.75,"high":21.53,"low":19.4,"close":21.53,"pre_close":19.57,"vol":982436.07,"amount":2056080.603},{"trade_date":"20260302","open":22.58,"high":22.6,"low":19.38,"close":21.5,"pre_close":21.53,"vol":1740062.04,"amount":3635844.694},{"trade_date":"20260303","open":21.5,"high":21.6,"low":19.35,"close":19.35,"pre_close":21.5,"vol":1258584.35,"amount":2539358.132},{"trade_date":"20260304","open":17.42,"high":20.0,"low":17.42,"close":18.57,"pre_close":19.35,"vol":1375982.04,"amount":2601332.137},{"trade_date":"20260305","open":19.19,"high":19.33,"low":18.0,"close":18.17,"pre_close":18.57,"vol":934148.51,"amount":1721719.064},{"trade_date":"20260306","open":18.16,"high":19.99,"low":17.9,"close":19.99,"pre_close":18.17,"vol":1011128.11,"amount":1941283.761},{"trade_date":"20260309","open":20.36,"high":20.84,"low":18.66,"close":20.47,"pre_close":19.99,"vol":1257331.86,"amount":2472464.951},{"trade_date":"20260310","open":20.3,"high":21.0,"low":18.8,"close":19.2,"pre_close":20.47,"vol":1098598.23,"amount":2131481.102},{"trade_date":"20260311","open":19.5,"high":19.96,"low":18.31,"close":18.42,"pre_close":19.2,"vol":988273.24,"amount":1887686.511},{"trade_date":"20260312","open":18.47,"high":18.58,"low":17.49,"close":17.73,"pre_close":18.42,"vol":688537.95,"amount":1234027.689},{"trade_date":"20260313","open":17.43,"high":17.5,"low":15.96,"close":15.96,"pre_close":17.73,"vol":926615.27,"amount":1514290.37},{"trade_date":"20260316","open":15.3,"high":16.55,"low":15.3,"close":16.37,"pre_close":15.96,"vol":841203.02,"amount":1347468.593},{"trade_date":"20260317","open":16.47,"high":17.2,"low":16.34,"close":16.5,"pre_close":16.37,"vol":743555.77,"amount":1243148.719},{"trade_date":"20260318","open":16.5,"high":17.8,"low":16.5,"close":17.49,"pre_close":16.5,"vol":800911.22,"amount":1395556.725},{"trade_date":"20260319","open":17.01,"high":17.1,"low":15.9,"close":16.03,"pre_close":17.49,"vol":712588.02,"amount":1164515.365},{"trade_date":"20260320","open":16.46,"high":16.75,"low":15.44,"close":15.51,"pre_close":16.03,"vol":667425.02,"amount":1071435.792},{"trade_date":"20260323","open":15.28,"high":15.45,"low":14.36,"close":14.5,"pre_close":15.51,"vol":697194.18,"amount":1037360.792},{"trade_date":"20260324","open":14.99,"high":15.2,"low":14.33,"close":15.17,"pre_close":14.5,"vol":610663.33,"amount":903652.78},{"trade_date":"20260325","open":15.55,"high":15.71,"low":15.02,"close":15.18,"pre_close":15.17,"vol":458366.0,"amount":699432.311},{"trade_date":"20260326","open":15.81,"high":16.35,"low":14.63,"close":14.73,"pre_close":15.18,"vol":657656.0,"amount":1005822.903},{"trade_date":"20260327","open":14.39,"high":15.57,"low":14.35,"close":15.17,"pre_close":14.73,"vol":620348.0,"amount":936695.808},{"trade_date":"20260330","open":15.17,"high":15.28,"low":14.86,"close":15.21,"pre_close":15.17,"vol":422940.0,"amount":636875.265},{"trade_date":"20260331","open":15.13,"high":15.3,"low":14.6,"close":14.7,"pre_close":15.21,"vol":401994.87,"amount":599185.68},{"trade_date":"20260401","open":15.06,"high":15.16,"low":14.66,"close":14.76,"pre_close":14.7,"vol":327867.0,"amount":487410.82},{"trade_date":"20260402","open":14.57,"high":14.85,"low":14.11,"close":14.23,"pre_close":14.76,"vol":322127.0,"amount":462673.573},{"trade_date":"20260403","open":14.27,"high":14.32,"low":13.71,"close":13.75,"pre_close":14.23,"vol":334907.75,"amount":465988.562},{"trade_date":"20260407","open":14.02,"high":14.46,"low":13.8,"close":14.1,"pre_close":13.75,"vol":323584.8,"amount":457406.349},{"trade_date":"20260408","open":14.56,"high":14.92,"low":14.35,"close":14.9,"pre_close":14.1,"vol":442957.73,"amount":650122.936},{"trade_date":"20260409","open":14.58,"high":15.0,"low":14.39,"close":14.75,"pre_close":14.9,"vol":356593.02,"amount":524591.046},{"trade_date":"20260410","open":14.9,"high":15.08,"low":14.58,"close":14.58,"pre_close":14.75,"vol":291732.0,"amount":430990.334},{"trade_date":"20260413","open":14.4,"high":14.69,"low":14.34,"close":14.45,"pre_close":14.58,"vol":291316.0,"amount":421322.753},{"trade_date":"20260414","open":14.66,"high":14.85,"low":14.45,"close":14.57,"pre_close":14.45,"vol":277774.98,"amount":405787.417},{"trade_date":"20260415","open":14.6,"high":14.85,"low":14.09,"close":14.13,"pre_close":14.57,"vol":329387.0,"amount":475098.972},{"trade_date":"20260416","open":14.09,"high":15.3,"low":14.01,"close":14.88,"pre_close":14.13,"vol":613855.9,"amount":904908.886},{"trade_date":"20260417","open":14.88,"high":15.37,"low":14.7,"close":15.15,"pre_close":14.88,"vol":624614.0,"amount":942586.513},{"trade_date":"20260420","open":14.95,"high":15.29,"low":14.87,"close":15.01,"pre_close":15.15,"vol":494678.97,"amount":743037.527},{"trade_date":"20260421","open":15.0,"high":15.36,"low":14.54,"close":14.99,"pre_close":15.01,"vol":471124.0,"amount":707462.594},{"trade_date":"20260422","open":14.94,"high":15.48,"low":14.6,"close":15.24,"pre_close":14.99,"vol":531188.35,"amount":803273.797},{"trade_date":"20260423","open":15.16,"high":15.27,"low":14.42,"close":14.63,"pre_close":15.24,"vol":531479.0,"amount":779960.088},{"trade_date":"20260424","open":14.5,"high":14.6,"low":13.78,"close":14.02,"pre_close":14.63,"vol":486614.56,"amount":685847.746},{"trade_date":"20260427","open":13.95,"high":13.99,"low":13.01,"close":13.3,"pre_close":14.02,"vol":549174.32,"amount":728885.593},{"trade_date":"20260428","open":13.23,"high":13.36,"low":12.84,"close":13.2,"pre_close":13.3,"vol":335020.0,"amount":439726.668},{"trade_date":"20260429","open":13.22,"high":14.52,"low":13.03,"close":14.52,"pre_close":13.2,"vol":489472.17,"amount":687194.389},{"trade_date":"20260430","open":14.7,"high":14.73,"low":14.31,"close":14.35,"pre_close":14.52,"vol":615510.2,"amount":891405.754},{"trade_date":"20260506","open":14.23,"high":14.76,"low":14.1,"close":14.62,"pre_close":14.35,"vol":421349.96,"amount":608881.543},{"trade_date":"20260507","open":14.61,"high":15.15,"low":14.48,"close":15.02,"pre_close":14.62,"vol":484193.2,"amount":718766.186},{"trade_date":"20260508","open":14.95,"high":16.03,"low":14.78,"close":15.36,"pre_close":15.02,"vol":680318.95,"amount":1055309.704},{"trade_date":"20260511","open":15.67,"high":15.68,"low":15.09,"close":15.19,"pre_close":15.36,"vol":424057.0,"amount":650661.495},{"trade_date":"20260512","open":15.23,"high":15.38,"low":14.73,"close":14.9,"pre_close":15.19,"vol":287359.03,"amount":429390.436},{"trade_date":"20260513","open":14.87,"high":15.38,"low":14.78,"close":15.09,"pre_close":14.9,"vol":358361.0,"amount":539940.143},{"trade_date":"20260514","open":14.96,"high":15.0,"low":14.25,"close":14.27,"pre_close":15.09,"vol":351951.95,"amount":512811.289},{"trade_date":"20260515","open":14.2,"high":14.26,"low":13.8,"close":13.94,"pre_close":14.27,"vol":291093.95,"amount":406516.346},{"trade_date":"20260518","open":13.7,"high":14.25,"low":13.7,"close":13.96,"pre_close":13.94,"vol":242659.01,"amount":339183.677},{"trade_date":"20260519","open":14.09,"high":14.09,"low":13.4,"close":13.74,"pre_close":13.96,"vol":226831.02,"amount":308908.991},{"trade_date":"20260520","open":13.65,"high":13.77,"low":12.96,"close":13.17,"pre_close":13.74,"vol":369640.34,"amount":488466.233},{"trade_date":"20260521","open":13.1,"high":13.63,"low":12.77,"close":12.77,"pre_close":13.17,"vol":350718.01,"amount":463396.169},{"trade_date":"20260522","open":12.9,"high":13.5,"low":12.77,"close":13.34,"pre_close":12.77,"vol":272689.02,"amount":358717.599},{"trade_date":"20260525","open":13.34,"high":13.56,"low":13.07,"close":13.1,"pre_close":13.34,"vol":260927.0,"amount":346142.739},{"trade_date":"20260526","open":13.0,"high":14.25,"low":12.84,"close":13.95,"pre_close":13.1,"vol":533181.9,"amount":732863.385},{"trade_date":"20260527","open":14.07,"high":15.12,"low":13.66,"close":13.68,"pre_close":13.95,"vol":718126.42,"amount":1038692.752},{"trade_date":"20260528","open":13.68,"high":14.05,"low":13.41,"close":13.72,"pre_close":13.68,"vol":359020.0,"amount":490086.517},{"trade_date":"20260529","open":13.83,"high":14.49,"low":13.35,"close":13.94,"pre_close":13.72,"vol":512793.0,"amount":717455.279},{"trade_date":"20260601","open":13.93,"high":14.22,"low":13.35,"close":13.38,"pre_close":13.94,"vol":375031.6,"amount":513537.204},{"trade_date":"20260602","open":13.26,"high":13.86,"low":12.81,"close":13.69,"pre_close":13.38,"vol":444889.0,"amount":593959.876},{"trade_date":"20260603","open":13.54,"high":14.28,"low":13.45,"close":14.07,"pre_close":13.69,"vol":500373.8,"amount":702743.261},{"trade_date":"20260604","open":14.04,"high":14.08,"low":13.6,"close":13.92,"pre_close":14.07,"vol":356686.8,"amount":494613.11},{"trade_date":"20260605","open":13.93,"high":14.08,"low":13.46,"close":13.62,"pre_close":13.92,"vol":337026.0,"amount":463818.937},{"trade_date":"20260608","open":13.02,"high":14.18,"low":13.02,"close":13.5,"pre_close":13.62,"vol":441104.0,"amount":601518.325},{"trade_date":"20260609","open":13.58,"high":14.1,"low":13.35,"close":14.07,"pre_close":13.5,"vol":473189.0,"amount":650700.834},{"trade_date":"20260610","open":14.02,"high":14.4,"low":13.6,"close":13.82,"pre_close":14.07,"vol":390327.0,"amount":544600.408},{"trade_date":"20260611","open":13.9,"high":14.59,"low":13.72,"close":14.26,"pre_close":13.82,"vol":696238.93,"amount":988993.559},{"trade_date":"20260612","open":14.2,"high":15.44,"low":14.05,"close":14.72,"pre_close":14.26,"vol":947864.28,"amount":1394078.192},{"trade_date":"20260615","open":15.45,"high":15.59,"low":14.84,"close":15.17,"pre_close":14.72,"vol":796553.58,"amount":1213843.194},{"trade_date":"20260616","open":15.01,"high":16.69,"low":14.94,"close":16.69,"pre_close":15.17,"vol":665710.67,"amount":1082842.606},{"trade_date":"20260617","open":17.11,"high":18.36,"low":16.51,"close":18.36,"pre_close":16.69,"vol":1457804.91,"amount":2570234.408},{"trade_date":"20260618","open":18.36,"high":20.2,"low":17.98,"close":20.2,"pre_close":18.36,"vol":1537511.55,"amount":2956050.656},{"trade_date":"20260622","open":21.98,"high":22.22,"low":21.98,"close":22.22,"pre_close":20.2,"vol":251224.01,"amount":556683.798},{"trade_date":"20260623","open":24.44,"high":24.44,"low":23.6,"close":24.44,"pre_close":22.22,"vol":1780059.91,"amount":4335002.474},{"trade_date":"20260624","open":24.83,"high":26.87,"low":22.8,"close":25.51,"pre_close":24.44,"vol":2072916.46,"amount":5185322.185},{"trade_date":"20260625","open":25.63,"high":26.18,"low":24.42,"close":25.68,"pre_close":25.51,"vol":1183348.71,"amount":2989878.536},{"trade_date":"20260626","open":25.4,"high":27.15,"low":24.8,"close":26.04,"pre_close":25.68,"vol":1012856.06,"amount":2635947.96},{"trade_date":"20260629","open":26.49,"high":28.64,"low":26.48,"close":27.5,"pre_close":26.04,"vol":1164705.54,"amount":3216436.785},{"trade_date":"20260630","open":28.13,"high":29.49,"low":26.62,"close":27.23,"pre_close":27.5,"vol":1208837.32,"amount":3379261.335},{"trade_date":"20260701","open":27.4,"high":29.95,"low":27.4,"close":29.95,"pre_close":27.23,"vol":416111.0,"amount":1216275.127},{"trade_date":"20260702","open":29.48,"high":31.79,"low":28.5,"close":28.5,"pre_close":29.95,"vol":1414764.56,"amount":4281278.225},{"trade_date":"20260703","open":27.88,"high":28.49,"low":25.65,"close":25.65,"pre_close":28.5,"vol":1431499.89,"amount":3839382.601},{"trade_date":"20260706","open":25.0,"high":26.03,"low":23.09,"close":23.09,"pre_close":25.65,"vol":887985.3,"amount":2162708.964},{"trade_date":"20260707","open":22.5,"high":22.61,"low":20.78,"close":20.78,"pre_close":23.09,"vol":957632.95,"amount":2064847.473},{"trade_date":"20260708","open":20.88,"high":21.28,"low":19.01,"close":19.14,"pre_close":20.78,"vol":943169.61,"amount":1874668.351},{"trade_date":"20260709","open":19.41,"high":19.86,"low":18.45,"close":19.86,"pre_close":19.14,"vol":797398.0,"amount":1535178.516},{"trade_date":"20260710","open":19.55,"high":20.54,"low":18.82,"close":18.84,"pre_close":19.86,"vol":726069.01,"amount":1434194.423},{"trade_date":"20260713","open":18.8,"high":19.17,"low":17.28,"close":17.5,"pre_close":18.84,"vol":651902.24,"amount":1184590.792}],"signal_dates":["20260706","20260707","20260709"],"generated_at":"2026-07-13T09:32:52+00:00"}