{"ts_code":"688216.SH","name":"气派科技","count":120,"kline":[{"trade_date":"20251205","open":21.85,"high":22.38,"low":21.29,"close":22.32,"pre_close":21.9,"vol":22383.08,"amount":49163.287},{"trade_date":"20251208","open":22.32,"high":23.06,"low":22.31,"close":22.76,"pre_close":22.32,"vol":16065.4,"amount":36621.14},{"trade_date":"20251209","open":22.69,"high":23.08,"low":22.27,"close":22.35,"pre_close":22.76,"vol":12187.24,"amount":27459.682},{"trade_date":"20251210","open":22.2,"high":22.41,"low":21.81,"close":22.0,"pre_close":22.35,"vol":10964.02,"amount":24190.23},{"trade_date":"20251211","open":22.14,"high":22.28,"low":21.36,"close":21.38,"pre_close":22.0,"vol":14731.71,"amount":31905.495},{"trade_date":"20251212","open":21.31,"high":21.89,"low":21.12,"close":21.17,"pre_close":21.38,"vol":13266.71,"amount":28351.451},{"trade_date":"20251215","open":21.31,"high":21.63,"low":20.89,"close":21.27,"pre_close":21.17,"vol":14223.03,"amount":30243.288},{"trade_date":"20251216","open":21.23,"high":21.34,"low":20.59,"close":20.87,"pre_close":21.27,"vol":15730.76,"amount":32790.432},{"trade_date":"20251217","open":20.74,"high":21.19,"low":20.03,"close":20.92,"pre_close":20.87,"vol":23735.4,"amount":48574.404},{"trade_date":"20251218","open":20.71,"high":21.84,"low":20.71,"close":21.28,"pre_close":20.92,"vol":20686.91,"amount":44501.756},{"trade_date":"20251219","open":21.63,"high":22.02,"low":21.45,"close":21.76,"pre_close":21.28,"vol":17701.01,"amount":38480.046},{"trade_date":"20251222","open":21.93,"high":22.53,"low":21.59,"close":22.12,"pre_close":21.76,"vol":18766.3,"amount":41752.485},{"trade_date":"20251223","open":22.05,"high":22.43,"low":21.73,"close":21.9,"pre_close":22.12,"vol":9693.86,"amount":21296.18},{"trade_date":"20251224","open":21.9,"high":22.35,"low":21.78,"close":22.14,"pre_close":21.9,"vol":10102.6,"amount":22379.754},{"trade_date":"20251225","open":22.17,"high":22.5,"low":22.05,"close":22.24,"pre_close":22.14,"vol":11216.26,"amount":24998.089},{"trade_date":"20251226","open":22.35,"high":22.52,"low":22.0,"close":22.04,"pre_close":22.24,"vol":10459.34,"amount":23253.272},{"trade_date":"20251229","open":22.1,"high":22.25,"low":21.82,"close":22.02,"pre_close":22.04,"vol":10581.35,"amount":23240.274},{"trade_date":"20251230","open":22.04,"high":22.95,"low":21.97,"close":22.23,"pre_close":22.02,"vol":21165.77,"amount":47514.153},{"trade_date":"20251231","open":22.6,"high":22.6,"low":21.98,"close":22.28,"pre_close":22.23,"vol":12001.68,"amount":26719.514},{"trade_date":"20260105","open":22.4,"high":23.12,"low":22.4,"close":22.97,"pre_close":22.28,"vol":16094.05,"amount":36746.853},{"trade_date":"20260106","open":22.88,"high":23.2,"low":22.62,"close":22.97,"pre_close":22.97,"vol":16069.67,"amount":36955.512},{"trade_date":"20260107","open":23.08,"high":23.3,"low":22.9,"close":23.23,"pre_close":22.97,"vol":16655.5,"amount":38558.513},{"trade_date":"20260108","open":23.23,"high":23.75,"low":23.01,"close":23.5,"pre_close":23.23,"vol":15178.49,"amount":35644.559},{"trade_date":"20260109","open":23.62,"high":24.58,"low":23.28,"close":23.76,"pre_close":23.5,"vol":17965.36,"amount":42679.696},{"trade_date":"20260112","open":23.81,"high":24.3,"low":23.5,"close":24.29,"pre_close":23.76,"vol":18624.07,"amount":44727.059},{"trade_date":"20260113","open":24.75,"high":25.03,"low":23.9,"close":23.98,"pre_close":24.29,"vol":21867.21,"amount":53050.366},{"trade_date":"20260114","open":23.98,"high":24.76,"low":23.57,"close":24.2,"pre_close":23.98,"vol":22249.41,"amount":53917.603},{"trade_date":"20260115","open":23.96,"high":24.9,"low":23.7,"close":24.74,"pre_close":24.2,"vol":23416.3,"amount":57059.583},{"trade_date":"20260116","open":25.23,"high":26.41,"low":24.64,"close":25.79,"pre_close":24.74,"vol":62597.65,"amount":160386.085},{"trade_date":"20260119","open":25.6,"high":27.29,"low":25.58,"close":26.91,"pre_close":25.79,"vol":55186.1,"amount":145973.648},{"trade_date":"20260120","open":26.88,"high":27.55,"low":26.61,"close":26.9,"pre_close":26.91,"vol":40383.3,"amount":109245.622},{"trade_date":"20260121","open":27.2,"high":29.09,"low":26.8,"close":28.74,"pre_close":26.9,"vol":52767.63,"amount":148302.981},{"trade_date":"20260122","open":28.65,"high":29.05,"low":27.36,"close":27.96,"pre_close":28.74,"vol":41434.47,"amount":115703.233},{"trade_date":"20260123","open":27.98,"high":29.25,"low":27.83,"close":29.02,"pre_close":27.96,"vol":38938.03,"amount":111002.455},{"trade_date":"20260126","open":28.71,"high":29.17,"low":27.03,"close":27.5,"pre_close":29.02,"vol":41587.76,"amount":115153.467},{"trade_date":"20260127","open":27.55,"high":28.52,"low":26.9,"close":28.31,"pre_close":27.5,"vol":43028.83,"amount":119910.602},{"trade_date":"20260128","open":30.69,"high":33.97,"low":30.5,"close":33.97,"pre_close":28.31,"vol":41372.34,"amount":137186.345},{"trade_date":"20260129","open":35.0,"high":35.6,"low":32.0,"close":35.0,"pre_close":33.97,"vol":141053.37,"amount":474330.817},{"trade_date":"20260130","open":33.66,"high":35.48,"low":32.14,"close":34.19,"pre_close":35.0,"vol":109528.0,"amount":368631.52},{"trade_date":"20260202","open":33.0,"high":33.99,"low":30.5,"close":30.5,"pre_close":34.19,"vol":84549.17,"amount":267619.826},{"trade_date":"20260203","open":30.87,"high":31.25,"low":30.0,"close":30.8,"pre_close":30.5,"vol":58416.47,"amount":178950.708},{"trade_date":"20260204","open":30.35,"high":30.53,"low":29.66,"close":30.25,"pre_close":30.8,"vol":45922.88,"amount":138248.774},{"trade_date":"20260205","open":29.82,"high":31.27,"low":29.04,"close":31.21,"pre_close":30.25,"vol":57687.27,"amount":173504.422},{"trade_date":"20260206","open":30.66,"high":30.66,"low":29.33,"close":29.73,"pre_close":31.21,"vol":44124.99,"amount":132193.577},{"trade_date":"20260209","open":30.0,"high":30.92,"low":29.82,"close":29.92,"pre_close":29.73,"vol":44322.13,"amount":134372.457},{"trade_date":"20260210","open":30.03,"high":31.14,"low":29.6,"close":29.88,"pre_close":29.92,"vol":36190.2,"amount":109398.93},{"trade_date":"20260211","open":30.5,"high":31.08,"low":30.05,"close":30.26,"pre_close":29.88,"vol":33814.49,"amount":103082.897},{"trade_date":"20260212","open":30.06,"high":31.68,"low":30.06,"close":31.25,"pre_close":30.26,"vol":39433.0,"amount":121759.311},{"trade_date":"20260213","open":31.0,"high":31.71,"low":30.4,"close":30.47,"pre_close":31.25,"vol":33134.94,"amount":103000.837},{"trade_date":"20260224","open":30.8,"high":31.87,"low":30.34,"close":31.29,"pre_close":30.47,"vol":37755.43,"amount":117247.457},{"trade_date":"20260225","open":31.26,"high":31.7,"low":30.59,"close":31.62,"pre_close":31.29,"vol":30560.67,"amount":95083.92},{"trade_date":"20260226","open":31.61,"high":33.14,"low":31.15,"close":32.8,"pre_close":31.62,"vol":40970.59,"amount":132839.962},{"trade_date":"20260227","open":32.64,"high":35.4,"low":31.83,"close":34.67,"pre_close":32.8,"vol":55433.84,"amount":189303.357},{"trade_date":"20260302","open":33.41,"high":34.08,"low":32.9,"close":33.12,"pre_close":34.67,"vol":45606.82,"amount":151996.234},{"trade_date":"20260303","open":32.91,"high":33.45,"low":30.52,"close":30.94,"pre_close":33.12,"vol":39064.62,"amount":124120.639},{"trade_date":"20260304","open":30.0,"high":31.56,"low":30.0,"close":30.8,"pre_close":30.94,"vol":22100.55,"amount":68239.12},{"trade_date":"20260305","open":31.44,"high":31.86,"low":30.73,"close":31.1,"pre_close":30.8,"vol":19663.12,"amount":61610.019},{"trade_date":"20260306","open":30.88,"high":31.65,"low":30.67,"close":31.23,"pre_close":31.1,"vol":19866.71,"amount":62010.884},{"trade_date":"20260309","open":30.2,"high":31.01,"low":29.5,"close":30.68,"pre_close":31.23,"vol":28008.08,"amount":84543.093},{"trade_date":"20260310","open":31.2,"high":32.44,"low":31.06,"close":32.2,"pre_close":30.68,"vol":25290.86,"amount":80526.709},{"trade_date":"20260311","open":32.15,"high":32.86,"low":31.1,"close":31.3,"pre_close":32.2,"vol":22536.61,"amount":71813.981},{"trade_date":"20260312","open":31.07,"high":31.35,"low":29.66,"close":29.86,"pre_close":31.3,"vol":31777.84,"amount":96081.732},{"trade_date":"20260313","open":29.86,"high":30.94,"low":29.64,"close":29.85,"pre_close":29.86,"vol":20351.66,"amount":61383.778},{"trade_date":"20260316","open":29.86,"high":30.97,"low":29.19,"close":30.53,"pre_close":29.85,"vol":24817.47,"amount":74818.334},{"trade_date":"20260317","open":30.49,"high":30.63,"low":29.2,"close":29.36,"pre_close":30.53,"vol":22129.0,"amount":66311.007},{"trade_date":"20260318","open":29.88,"high":30.38,"low":29.62,"close":30.38,"pre_close":29.36,"vol":16588.96,"amount":49869.727},{"trade_date":"20260319","open":29.82,"high":30.17,"low":29.17,"close":29.3,"pre_close":30.38,"vol":20714.8,"amount":61510.281},{"trade_date":"20260320","open":29.28,"high":29.93,"low":28.28,"close":28.3,"pre_close":29.3,"vol":20057.54,"amount":58239.997},{"trade_date":"20260323","open":27.37,"high":27.99,"low":25.77,"close":25.93,"pre_close":28.3,"vol":36237.39,"amount":97355.445},{"trade_date":"20260324","open":26.97,"high":27.47,"low":26.15,"close":27.46,"pre_close":25.93,"vol":22025.83,"amount":58842.044},{"trade_date":"20260325","open":27.0,"high":28.58,"low":27.0,"close":27.89,"pre_close":27.46,"vol":20622.75,"amount":57846.881},{"trade_date":"20260326","open":27.99,"high":27.99,"low":26.45,"close":26.63,"pre_close":27.89,"vol":21868.14,"amount":59091.442},{"trade_date":"20260327","open":26.58,"high":27.84,"low":26.0,"close":27.25,"pre_close":26.63,"vol":21728.98,"amount":58722.583},{"trade_date":"20260330","open":26.53,"high":27.8,"low":26.29,"close":27.61,"pre_close":27.25,"vol":19126.31,"amount":52162.051},{"trade_date":"20260331","open":27.6,"high":28.11,"low":26.9,"close":26.9,"pre_close":27.61,"vol":18347.11,"amount":50434.811},{"trade_date":"20260401","open":28.2,"high":28.7,"low":27.19,"close":27.59,"pre_close":26.9,"vol":20406.78,"amount":56399.103},{"trade_date":"20260402","open":27.56,"high":28.1,"low":26.65,"close":26.66,"pre_close":27.59,"vol":22643.85,"amount":62060.875},{"trade_date":"20260403","open":27.22,"high":27.5,"low":26.34,"close":26.34,"pre_close":26.66,"vol":20591.51,"amount":55191.673},{"trade_date":"20260407","open":26.46,"high":27.74,"low":26.46,"close":26.91,"pre_close":26.34,"vol":20029.87,"amount":54096.045},{"trade_date":"20260408","open":27.48,"high":28.77,"low":27.48,"close":28.76,"pre_close":26.91,"vol":20498.46,"amount":57794.625},{"trade_date":"20260409","open":28.55,"high":29.01,"low":28.27,"close":28.48,"pre_close":28.76,"vol":21388.52,"amount":61236.276},{"trade_date":"20260410","open":28.64,"high":29.13,"low":28.32,"close":28.38,"pre_close":28.48,"vol":17979.64,"amount":51629.05},{"trade_date":"20260413","open":28.4,"high":29.25,"low":28.11,"close":28.51,"pre_close":28.38,"vol":25304.57,"amount":72600.635},{"trade_date":"20260414","open":28.83,"high":29.26,"low":28.64,"close":29.02,"pre_close":28.51,"vol":21429.01,"amount":62155.043},{"trade_date":"20260415","open":29.02,"high":29.5,"low":28.6,"close":28.69,"pre_close":29.02,"vol":20011.7,"amount":58047.153},{"trade_date":"20260416","open":28.99,"high":29.78,"low":28.64,"close":29.49,"pre_close":28.69,"vol":25614.33,"amount":75032.941},{"trade_date":"20260417","open":29.97,"high":29.97,"low":29.27,"close":29.33,"pre_close":29.49,"vol":17139.29,"amount":50592.892},{"trade_date":"20260420","open":29.17,"high":29.7,"low":29.03,"close":29.03,"pre_close":29.33,"vol":16692.28,"amount":48864.425},{"trade_date":"20260421","open":29.08,"high":29.11,"low":28.33,"close":28.72,"pre_close":29.03,"vol":16792.07,"amount":48105.713},{"trade_date":"20260422","open":28.64,"high":29.41,"low":28.64,"close":29.27,"pre_close":28.72,"vol":19138.77,"amount":55618.203},{"trade_date":"20260423","open":29.3,"high":29.69,"low":28.01,"close":28.26,"pre_close":29.27,"vol":19657.17,"amount":55971.209},{"trade_date":"20260424","open":28.03,"high":28.84,"low":27.83,"close":28.35,"pre_close":28.26,"vol":29929.6,"amount":85237.661},{"trade_date":"20260427","open":28.07,"high":29.8,"low":28.0,"close":29.74,"pre_close":28.35,"vol":23232.65,"amount":67731.038},{"trade_date":"20260428","open":29.42,"high":29.66,"low":28.02,"close":28.31,"pre_close":29.74,"vol":34909.32,"amount":99432.769},{"trade_date":"20260429","open":28.22,"high":29.2,"low":28.01,"close":28.79,"pre_close":28.31,"vol":28371.84,"amount":81632.353},{"trade_date":"20260430","open":29.29,"high":31.49,"low":28.82,"close":30.64,"pre_close":28.79,"vol":53495.61,"amount":162695.765},{"trade_date":"20260506","open":31.05,"high":32.38,"low":31.0,"close":31.76,"pre_close":30.64,"vol":52398.48,"amount":166590.061},{"trade_date":"20260507","open":31.76,"high":32.77,"low":31.49,"close":32.46,"pre_close":31.76,"vol":36088.58,"amount":116632.315},{"trade_date":"20260508","open":32.0,"high":33.54,"low":31.75,"close":32.95,"pre_close":32.46,"vol":36501.63,"amount":119290.868},{"trade_date":"20260511","open":33.37,"high":36.66,"low":33.18,"close":34.95,"pre_close":32.95,"vol":59003.42,"amount":204350.802},{"trade_date":"20260512","open":34.89,"high":36.66,"low":34.23,"close":35.0,"pre_close":34.95,"vol":64515.92,"amount":226957.971},{"trade_date":"20260513","open":34.4,"high":35.68,"low":33.04,"close":35.36,"pre_close":35.0,"vol":53531.51,"amount":186026.442},{"trade_date":"20260514","open":35.54,"high":36.48,"low":35.01,"close":35.4,"pre_close":35.36,"vol":54282.82,"amount":194217.03},{"trade_date":"20260515","open":35.35,"high":37.78,"low":34.88,"close":35.86,"pre_close":35.4,"vol":52544.2,"amount":188959.158},{"trade_date":"20260518","open":35.4,"high":36.7,"low":34.01,"close":36.02,"pre_close":35.86,"vol":53231.0,"amount":190684.252},{"trade_date":"20260519","open":36.6,"high":36.72,"low":35.08,"close":36.72,"pre_close":36.02,"vol":45694.44,"amount":164040.775},{"trade_date":"20260520","open":36.35,"high":38.51,"low":36.13,"close":37.57,"pre_close":36.72,"vol":75380.5,"amount":282509.904},{"trade_date":"20260521","open":37.78,"high":38.9,"low":34.5,"close":34.54,"pre_close":37.57,"vol":71952.07,"amount":263549.43},{"trade_date":"20260522","open":34.84,"high":36.32,"low":34.82,"close":36.0,"pre_close":34.54,"vol":64255.73,"amount":227861.705},{"trade_date":"20260525","open":35.7,"high":38.48,"low":35.7,"close":38.0,"pre_close":36.0,"vol":67641.7,"amount":253294.601},{"trade_date":"20260526","open":39.07,"high":41.4,"low":37.9,"close":39.59,"pre_close":38.0,"vol":88795.9,"amount":346743.791},{"trade_date":"20260527","open":39.2,"high":40.78,"low":37.58,"close":38.06,"pre_close":39.59,"vol":84556.53,"amount":328082.186},{"trade_date":"20260528","open":37.72,"high":39.0,"low":36.0,"close":38.33,"pre_close":38.06,"vol":65796.62,"amount":247907.52},{"trade_date":"20260529","open":38.01,"high":38.54,"low":34.39,"close":34.76,"pre_close":38.33,"vol":65370.02,"amount":233582.625},{"trade_date":"20260601","open":35.0,"high":35.0,"low":33.01,"close":33.16,"pre_close":34.76,"vol":58673.26,"amount":198015.387},{"trade_date":"20260602","open":33.23,"high":33.48,"low":31.64,"close":32.16,"pre_close":33.16,"vol":34704.46,"amount":112651.262},{"trade_date":"20260603","open":32.0,"high":33.9,"low":31.77,"close":32.42,"pre_close":32.16,"vol":37886.75,"amount":125067.964},{"trade_date":"20260604","open":32.13,"high":33.0,"low":31.54,"close":32.5,"pre_close":32.42,"vol":36712.9,"amount":119760.158},{"trade_date":"20260605","open":32.6,"high":32.75,"low":30.94,"close":31.55,"pre_close":32.5,"vol":35471.36,"amount":112619.612},{"trade_date":"20260608","open":30.33,"high":31.0,"low":28.95,"close":29.54,"pre_close":31.55,"vol":40693.0,"amount":122329.41}],"signal_dates":["20260529","20260601","20260604"],"generated_at":"2026-06-08T10:20:00+00:00"}